chkweb.py
chkweb-0.1.5.dist-info/entry_points.txt
chkweb-0.1.5.dist-info/LICENSE.txt
chkweb-0.1.5.dist-info/WHEEL
chkweb-0.1.5.dist-info/METADATA
chkweb-0.1.5.dist-info/RECORD
