Metadata-Version: 2.1
Name: chkweb
Version: 0.1.5
Summary: A very simple web crawler and checker
Home-page: https://github.com/euribates/chkweb.git
License: GPL-3.0-or-later
Author: Juan Ignacio Rodriguez de Leon
Author-email: euribates@gmail.com
Requires-Python: >=3.8,<4.0
Classifier: License :: OSI Approved :: GNU General Public License v3 or later (GPLv3+)
Classifier: Programming Language :: Python :: 3
Classifier: Programming Language :: Python :: 3.8
Classifier: Programming Language :: Python :: 3.9
Requires-Dist: fire (>=0.4.0,<0.5.0)
Requires-Dist: prettyconf (>=2.2.1,<3.0.0)
Requires-Dist: requests (>=2.25.1,<3.0.0)
Project-URL: Repository, https://github.com/euribates/chkweb.git
